[
    {
        "id": 1,
        "type": "branch",
        "events": [
            {
                "customer-request-id": 1,
                "logical_clock": 2,
                "interface": "deposit",
                "comment": "event_recv from customer 1"
            },
            {
                "customer-request-id": 1,
                "logical_clock": 3,
                "interface": "propogate_deposit",
                "comment": "event_sent to branch 2"
            },
            {
                "customer-request-id": 11,
                "logical_clock": 4,
                "interface": "propogate_deposit",
                "comment": "event_recv from bank 6"
            },
            {
                "customer-request-id": 1,
                "logical_clock": 5,
                "interface": "propogate_deposit",
                "comment": "event_sent to branch 3"
            },
            {
                "customer-request-id": 5,
                "logical_clock": 6,
                "interface": "propogate_deposit",
                "comment": "event_recv from bank 3"
            },
            {
                "customer-request-id": 3,
                "logical_clock": 7,
                "interface": "propogate_deposit",
                "comment": "event_recv from bank 2"
            },
            {
                "customer-request-id": 7,
                "logical_clock": 8,
                "interface": "propogate_deposit",
                "comment": "event_recv from bank 4"
            },
            {
                "customer-request-id": 1,
                "logical_clock": 9,
                "interface": "propogate_deposit",
                "comment": "event_sent to branch 4"
            },
            {
                "customer-request-id": 9,
                "logical_clock": 10,
                "interface": "propogate_deposit",
                "comment": "event_recv from bank 5"
            },
            {
                "customer-request-id": 17,
                "logical_clock": 11,
                "interface": "propogate_deposit",
                "comment": "event_recv from bank 9"
            },
            {
                "customer-request-id": 15,
                "logical_clock": 12,
                "interface": "propogate_deposit",
                "comment": "event_recv from bank 8"
            },
            {
                "customer-request-id": 19,
                "logical_clock": 13,
                "interface": "propogate_deposit",
                "comment": "event_recv from bank 10"
            },
            {
                "customer-request-id": 13,
                "logical_clock": 14,
                "interface": "propogate_deposit",
                "comment": "event_recv from bank 7"
            },
            {
                "customer-request-id": 1,
                "logical_clock": 15,
                "interface": "propogate_deposit",
                "comment": "event_sent to branch 5"
            },
            {
                "customer-request-id": 1,
                "logical_clock": 16,
                "interface": "propogate_deposit",
                "comment": "event_sent to branch 6"
            },
            {
                "customer-request-id": 1,
                "logical_clock": 17,
                "interface": "propogate_deposit",
                "comment": "event_sent to branch 7"
            },
            {
                "customer-request-id": 1,
                "logical_clock": 18,
                "interface": "propogate_deposit",
                "comment": "event_sent to branch 8"
            },
            {
                "customer-request-id": 1,
                "logical_clock": 19,
                "interface": "propogate_deposit",
                "comment": "event_sent to branch 9"
            },
            {
                "customer-request-id": 1,
                "logical_clock": 20,
                "interface": "propogate_deposit",
                "comment": "event_sent to branch 10"
            },
            {
                "customer-request-id": 12,
                "logical_clock": 31,
                "interface": "propogate_withdraw",
                "comment": "event_recv from bank 6"
            },
            {
                "customer-request-id": 6,
                "logical_clock": 32,
                "interface": "propogate_withdraw",
                "comment": "event_recv from bank 3"
            },
            {
                "customer-request-id": 18,
                "logical_clock": 36,
                "interface": "propogate_withdraw",
                "comment": "event_recv from bank 9"
            },
            {
                "customer-request-id": 8,
                "logical_clock": 37,
                "interface": "propogate_withdraw",
                "comment": "event_recv from bank 4"
            },
            {
                "customer-request-id": 2,
                "logical_clock": 38,
                "interface": "deposit",
                "comment": "event_recv from customer 1"
            },
            {
                "customer-request-id": 2,
                "logical_clock": 39,
                "interface": "propogate_withdraw",
                "comment": "event_sent to branch 2"
            },
            {
                "customer-request-id": 16,
                "logical_clock": 40,
                "interface": "propogate_withdraw",
                "comment": "event_recv from bank 8"
            },
            {
                "customer-request-id": 14,
                "logical_clock": 41,
                "interface": "propogate_withdraw",
                "comment": "event_recv from bank 7"
            },
            {
                "customer-request-id": 4,
                "logical_clock": 42,
                "interface": "propogate_withdraw",
                "comment": "event_recv from bank 2"
            },
            {
                "customer-request-id": 10,
                "logical_clock": 43,
                "interface": "propogate_withdraw",
                "comment": "event_recv from bank 5"
            },
            {
                "customer-request-id": 2,
                "logical_clock": 44,
                "interface": "propogate_withdraw",
                "comment": "event_sent to branch 3"
            },
            {
                "customer-request-id": 20,
                "logical_clock": 45,
                "interface": "propogate_withdraw",
                "comment": "event_recv from bank 10"
            },
            {
                "customer-request-id": 2,
                "logical_clock": 46,
                "interface": "propogate_withdraw",
                "comment": "event_sent to branch 4"
            },
            {
                "customer-request-id": 2,
                "logical_clock": 47,
                "interface": "propogate_withdraw",
                "comment": "event_sent to branch 5"
            },
            {
                "customer-request-id": 2,
                "logical_clock": 48,
                "interface": "propogate_withdraw",
                "comment": "event_sent to branch 6"
            },
            {
                "customer-request-id": 2,
                "logical_clock": 49,
                "interface": "propogate_withdraw",
                "comment": "event_sent to branch 7"
            },
            {
                "customer-request-id": 2,
                "logical_clock": 50,
                "interface": "propogate_withdraw",
                "comment": "event_sent to branch 8"
            },
            {
                "customer-request-id": 2,
                "logical_clock": 51,
                "interface": "propogate_withdraw",
                "comment": "event_sent to branch 9"
            },
            {
                "customer-request-id": 2,
                "logical_clock": 52,
                "interface": "propogate_withdraw",
                "comment": "event_sent to branch 10"
            }
        ]
    },
    {
        "id": 2,
        "type": "branch",
        "events": [
            {
                "customer-request-id": 3,
                "logical_clock": 2,
                "interface": "deposit",
                "comment": "event_recv from customer 2"
            },
            {
                "customer-request-id": 3,
                "logical_clock": 3,
                "interface": "propogate_deposit",
                "comment": "event_sent to branch 1"
            },
            {
                "customer-request-id": 1,
                "logical_clock": 4,
                "interface": "propogate_deposit",
                "comment": "event_recv from bank 1"
            },
            {
                "customer-request-id": 3,
                "logical_clock": 5,
                "interface": "propogate_deposit",
                "comment": "event_sent to branch 3"
            },
            {
                "customer-request-id": 11,
                "logical_clock": 6,
                "interface": "propogate_deposit",
                "comment": "event_recv from bank 6"
            },
            {
                "customer-request-id": 5,
                "logical_clock": 7,
                "interface": "propogate_deposit",
                "comment": "event_recv from bank 3"
            },
            {
                "customer-request-id": 7,
                "logical_clock": 8,
                "interface": "propogate_deposit",
                "comment": "event_recv from bank 4"
            },
            {
                "customer-request-id": 3,
                "logical_clock": 9,
                "interface": "propogate_deposit",
                "comment": "event_sent to branch 4"
            },
            {
                "customer-request-id": 17,
                "logical_clock": 10,
                "interface": "propogate_deposit",
                "comment": "event_recv from bank 9"
            },
            {
                "customer-request-id": 15,
                "logical_clock": 11,
                "interface": "propogate_deposit",
                "comment": "event_recv from bank 8"
            },
            {
                "customer-request-id": 19,
                "logical_clock": 12,
                "interface": "propogate_deposit",
                "comment": "event_recv from bank 10"
            },
            {
                "customer-request-id": 9,
                "logical_clock": 13,
                "interface": "propogate_deposit",
                "comment": "event_recv from bank 5"
            },
            {
                "customer-request-id": 13,
                "logical_clock": 14,
                "interface": "propogate_deposit",
                "comment": "event_recv from bank 7"
            },
            {
                "customer-request-id": 3,
                "logical_clock": 15,
                "interface": "propogate_deposit",
                "comment": "event_sent to branch 5"
            },
            {
                "customer-request-id": 3,
                "logical_clock": 16,
                "interface": "propogate_deposit",
                "comment": "event_sent to branch 6"
            },
            {
                "customer-request-id": 3,
                "logical_clock": 17,
                "interface": "propogate_deposit",
                "comment": "event_sent to branch 7"
            },
            {
                "customer-request-id": 3,
                "logical_clock": 18,
                "interface": "propogate_deposit",
                "comment": "event_sent to branch 8"
            },
            {
                "customer-request-id": 3,
                "logical_clock": 19,
                "interface": "propogate_deposit",
                "comment": "event_sent to branch 9"
            },
            {
                "customer-request-id": 3,
                "logical_clock": 20,
                "interface": "propogate_deposit",
                "comment": "event_sent to branch 10"
            },
            {
                "customer-request-id": 6,
                "logical_clock": 27,
                "interface": "propogate_withdraw",
                "comment": "event_recv from bank 3"
            },
            {
                "customer-request-id": 12,
                "logical_clock": 32,
                "interface": "propogate_withdraw",
                "comment": "event_recv from bank 6"
            },
            {
                "customer-request-id": 18,
                "logical_clock": 37,
                "interface": "propogate_withdraw",
                "comment": "event_recv from bank 9"
            },
            {
                "customer-request-id": 4,
                "logical_clock": 38,
                "interface": "deposit",
                "comment": "event_recv from customer 2"
            },
            {
                "customer-request-id": 4,
                "logical_clock": 39,
                "interface": "propogate_withdraw",
                "comment": "event_sent to branch 1"
            },
            {
                "customer-request-id": 2,
                "logical_clock": 40,
                "interface": "propogate_withdraw",
                "comment": "event_recv from bank 1"
            },
            {
                "customer-request-id": 8,
                "logical_clock": 41,
                "interface": "propogate_withdraw",
                "comment": "event_recv from bank 4"
            },
            {
                "customer-request-id": 16,
                "logical_clock": 42,
                "interface": "propogate_withdraw",
                "comment": "event_recv from bank 8"
            },
            {
                "customer-request-id": 14,
                "logical_clock": 43,
                "interface": "propogate_withdraw",
                "comment": "event_recv from bank 7"
            },
            {
                "customer-request-id": 4,
                "logical_clock": 44,
                "interface": "propogate_withdraw",
                "comment": "event_sent to branch 3"
            },
            {
                "customer-request-id": 10,
                "logical_clock": 45,
                "interface": "propogate_withdraw",
                "comment": "event_recv from bank 5"
            },
            {
                "customer-request-id": 20,
                "logical_clock": 46,
                "interface": "propogate_withdraw",
                "comment": "event_recv from bank 10"
            },
            {
                "customer-request-id": 4,
                "logical_clock": 47,
                "interface": "propogate_withdraw",
                "comment": "event_sent to branch 4"
            },
            {
                "customer-request-id": 4,
                "logical_clock": 48,
                "interface": "propogate_withdraw",
                "comment": "event_sent to branch 5"
            },
            {
                "customer-request-id": 4,
                "logical_clock": 49,
                "interface": "propogate_withdraw",
                "comment": "event_sent to branch 6"
            },
            {
                "customer-request-id": 4,
                "logical_clock": 50,
                "interface": "propogate_withdraw",
                "comment": "event_sent to branch 7"
            },
            {
                "customer-request-id": 4,
                "logical_clock": 51,
                "interface": "propogate_withdraw",
                "comment": "event_sent to branch 8"
            },
            {
                "customer-request-id": 4,
                "logical_clock": 52,
                "interface": "propogate_withdraw",
                "comment": "event_sent to branch 9"
            },
            {
                "customer-request-id": 4,
                "logical_clock": 53,
                "interface": "propogate_withdraw",
                "comment": "event_sent to branch 10"
            }
        ]
    },
    {
        "id": 3,
        "type": "branch",
        "events": [
            {
                "customer-request-id": 5,
                "logical_clock": 2,
                "interface": "deposit",
                "comment": "event_recv from customer 3"
            },
            {
                "customer-request-id": 5,
                "logical_clock": 3,
                "interface": "propogate_deposit",
                "comment": "event_sent to branch 1"
            },
            {
                "customer-request-id": 5,
                "logical_clock": 4,
                "interface": "propogate_deposit",
                "comment": "event_sent to branch 2"
            },
            {
                "customer-request-id": 1,
                "logical_clock": 6,
                "interface": "propogate_deposit",
                "comment": "event_recv from bank 1"
            },
            {
                "customer-request-id": 5,
                "logical_clock": 7,
                "interface": "propogate_deposit",
                "comment": "event_sent to branch 4"
            },
            {
                "customer-request-id": 3,
                "logical_clock": 8,
                "interface": "propogate_deposit",
                "comment": "event_recv from bank 2"
            },
            {
                "customer-request-id": 11,
                "logical_clock": 9,
                "interface": "propogate_deposit",
                "comment": "event_recv from bank 6"
            },
            {
                "customer-request-id": 5,
                "logical_clock": 10,
                "interface": "propogate_deposit",
                "comment": "event_sent to branch 5"
            },
            {
                "customer-request-id": 7,
                "logical_clock": 13,
                "interface": "propogate_deposit",
                "comment": "event_recv from bank 4"
            },
            {
                "customer-request-id": 17,
                "logical_clock": 14,
                "interface": "propogate_deposit",
                "comment": "event_recv from bank 9"
            },
            {
                "customer-request-id": 5,
                "logical_clock": 15,
                "interface": "propogate_deposit",
                "comment": "event_sent to branch 6"
            },
            {
                "customer-request-id": 15,
                "logical_clock": 16,
                "interface": "propogate_deposit",
                "comment": "event_recv from bank 8"
            },
            {
                "customer-request-id": 13,
                "logical_clock": 17,
                "interface": "propogate_deposit",
                "comment": "event_recv from bank 7"
            },
            {
                "customer-request-id": 19,
                "logical_clock": 18,
                "interface": "propogate_deposit",
                "comment": "event_recv from bank 10"
            },
            {
                "customer-request-id": 9,
                "logical_clock": 19,
                "interface": "propogate_deposit",
                "comment": "event_recv from bank 5"
            },
            {
                "customer-request-id": 5,
                "logical_clock": 20,
                "interface": "propogate_deposit",
                "comment": "event_sent to branch 7"
            },
            {
                "customer-request-id": 5,
                "logical_clock": 21,
                "interface": "propogate_deposit",
                "comment": "event_sent to branch 8"
            },
            {
                "customer-request-id": 5,
                "logical_clock": 22,
                "interface": "propogate_deposit",
                "comment": "event_sent to branch 9"
            },
            {
                "customer-request-id": 5,
                "logical_clock": 23,
                "interface": "propogate_deposit",
                "comment": "event_sent to branch 10"
            },
            {
                "customer-request-id": 6,
                "logical_clock": 24,
                "interface": "deposit",
                "comment": "event_recv from customer 3"
            },
            {
                "customer-request-id": 6,
                "logical_clock": 25,
                "interface": "propogate_withdraw",
                "comment": "event_sent to branch 1"
            },
            {
                "customer-request-id": 6,
                "logical_clock": 26,
                "interface": "propogate_withdraw",
                "comment": "event_sent to branch 2"
            },
            {
                "customer-request-id": 6,
                "logical_clock": 27,
                "interface": "propogate_withdraw",
                "comment": "event_sent to branch 4"
            },
            {
                "customer-request-id": 12,
                "logical_clock": 33,
                "interface": "propogate_withdraw",
                "comment": "event_recv from bank 6"
            },
            {
                "customer-request-id": 18,
                "logical_clock": 41,
                "interface": "propogate_withdraw",
                "comment": "event_recv from bank 9"
            },
            {
                "customer-request-id": 6,
                "logical_clock": 42,
                "interface": "propogate_withdraw",
                "comment": "event_sent to branch 5"
            },
            {
                "customer-request-id": 6,
                "logical_clock": 43,
                "interface": "propogate_withdraw",
                "comment": "event_sent to branch 6"
            },
            {
                "customer-request-id": 2,
                "logical_clock": 45,
                "interface": "propogate_withdraw",
                "comment": "event_recv from bank 1"
            },
            {
                "customer-request-id": 8,
                "logical_clock": 46,
                "interface": "propogate_withdraw",
                "comment": "event_recv from bank 4"
            },
            {
                "customer-request-id": 4,
                "logical_clock": 47,
                "interface": "propogate_withdraw",
                "comment": "event_recv from bank 2"
            },
            {
                "customer-request-id": 16,
                "logical_clock": 48,
                "interface": "propogate_withdraw",
                "comment": "event_recv from bank 8"
            },
            {
                "customer-request-id": 14,
                "logical_clock": 49,
                "interface": "propogate_withdraw",
                "comment": "event_recv from bank 7"
            },
            {
                "customer-request-id": 6,
                "logical_clock": 50,
                "interface": "propogate_withdraw",
                "comment": "event_sent to branch 7"
            },
            {
                "customer-request-id": 10,
                "logical_clock": 51,
                "interface": "propogate_withdraw",
                "comment": "event_recv from bank 5"
            },
            {
                "customer-request-id": 6,
                "logical_clock": 52,
                "interface": "propogate_withdraw",
                "comment": "event_sent to branch 8"
            },
            {
                "customer-request-id": 20,
                "logical_clock": 53,
                "interface": "propogate_withdraw",
                "comment": "event_recv from bank 10"
            },
            {
                "customer-request-id": 6,
                "logical_clock": 54,
                "interface": "propogate_withdraw",
                "comment": "event_sent to branch 9"
            },
            {
                "customer-request-id": 6,
                "logical_clock": 55,
                "interface": "propogate_withdraw",
                "comment": "event_sent to branch 10"
            }
        ]
    },
    {
        "id": 4,
        "type": "branch",
        "events": [
            {
                "customer-request-id": 7,
                "logical_clock": 2,
                "interface": "deposit",
                "comment": "event_recv from customer 4"
            },
            {
                "customer-request-id": 7,
                "logical_clock": 3,
                "interface": "propogate_deposit",
                "comment": "event_sent to branch 1"
            },
            {
                "customer-request-id": 7,
                "logical_clock": 4,
                "interface": "propogate_deposit",
                "comment": "event_sent to branch 2"
            },
            {
                "customer-request-id": 1,
                "logical_clock": 10,
                "interface": "propogate_deposit",
                "comment": "event_recv from bank 1"
            },
            {
                "customer-request-id": 5,
                "logical_clock": 11,
                "interface": "propogate_deposit",
                "comment": "event_recv from bank 3"
            },
            {
                "customer-request-id": 7,
                "logical_clock": 12,
                "interface": "propogate_deposit",
                "comment": "event_sent to branch 3"
            },
            {
                "customer-request-id": 3,
                "logical_clock": 13,
                "interface": "propogate_deposit",
                "comment": "event_recv from bank 2"
            },
            {
                "customer-request-id": 11,
                "logical_clock": 14,
                "interface": "propogate_deposit",
                "comment": "event_recv from bank 6"
            },
            {
                "customer-request-id": 7,
                "logical_clock": 15,
                "interface": "propogate_deposit",
                "comment": "event_sent to branch 5"
            },
            {
                "customer-request-id": 7,
                "logical_clock": 16,
                "interface": "propogate_deposit",
                "comment": "event_sent to branch 6"
            },
            {
                "customer-request-id": 17,
                "logical_clock": 17,
                "interface": "propogate_deposit",
                "comment": "event_recv from bank 9"
            },
            {
                "customer-request-id": 15,
                "logical_clock": 18,
                "interface": "propogate_deposit",
                "comment": "event_recv from bank 8"
            },
            {
                "customer-request-id": 13,
                "logical_clock": 19,
                "interface": "propogate_deposit",
                "comment": "event_recv from bank 7"
            },
            {
                "customer-request-id": 7,
                "logical_clock": 20,
                "interface": "propogate_deposit",
                "comment": "event_sent to branch 7"
            },
            {
                "customer-request-id": 19,
                "logical_clock": 21,
                "interface": "propogate_deposit",
                "comment": "event_recv from bank 10"
            },
            {
                "customer-request-id": 9,
                "logical_clock": 22,
                "interface": "propogate_deposit",
                "comment": "event_recv from bank 5"
            },
            {
                "customer-request-id": 7,
                "logical_clock": 23,
                "interface": "propogate_deposit",
                "comment": "event_sent to branch 8"
            },
            {
                "customer-request-id": 7,
                "logical_clock": 24,
                "interface": "propogate_deposit",
                "comment": "event_sent to branch 9"
            },
            {
                "customer-request-id": 7,
                "logical_clock": 25,
                "interface": "propogate_deposit",
                "comment": "event_sent to branch 10"
            },
            {
                "customer-request-id": 8,
                "logical_clock": 26,
                "interface": "deposit",
                "comment": "event_recv from customer 4"
            },
            {
                "customer-request-id": 8,
                "logical_clock": 27,
                "interface": "propogate_withdraw",
                "comment": "event_sent to branch 1"
            },
            {
                "customer-request-id": 8,
                "logical_clock": 28,
                "interface": "propogate_withdraw",
                "comment": "event_sent to branch 2"
            },
            {
                "customer-request-id": 6,
                "logical_clock": 29,
                "interface": "propogate_withdraw",
                "comment": "event_recv from bank 3"
            },
            {
                "customer-request-id": 12,
                "logical_clock": 34,
                "interface": "propogate_withdraw",
                "comment": "event_recv from bank 6"
            },
            {
                "customer-request-id": 8,
                "logical_clock": 35,
                "interface": "propogate_withdraw",
                "comment": "event_sent to branch 3"
            },
            {
                "customer-request-id": 18,
                "logical_clock": 42,
                "interface": "propogate_withdraw",
                "comment": "event_recv from bank 9"
            },
            {
                "customer-request-id": 8,
                "logical_clock": 43,
                "interface": "propogate_withdraw",
                "comment": "event_sent to branch 5"
            },
            {
                "customer-request-id": 2,
                "logical_clock": 47,
                "interface": "propogate_withdraw",
                "comment": "event_recv from bank 1"
            },
            {
                "customer-request-id": 16,
                "logical_clock": 48,
                "interface": "propogate_withdraw",
                "comment": "event_recv from bank 8"
            },
            {
                "customer-request-id": 14,
                "logical_clock": 54,
                "interface": "propogate_withdraw",
                "comment": "event_recv from bank 7"
            },
            {
                "customer-request-id": 4,
                "logical_clock": 55,
                "interface": "propogate_withdraw",
                "comment": "event_recv from bank 2"
            },
            {
                "customer-request-id": 8,
                "logical_clock": 56,
                "interface": "propogate_withdraw",
                "comment": "event_sent to branch 6"
            },
            {
                "customer-request-id": 8,
                "logical_clock": 57,
                "interface": "propogate_withdraw",
                "comment": "event_sent to branch 7"
            },
            {
                "customer-request-id": 20,
                "logical_clock": 58,
                "interface": "propogate_withdraw",
                "comment": "event_recv from bank 10"
            },
            {
                "customer-request-id": 10,
                "logical_clock": 59,
                "interface": "propogate_withdraw",
                "comment": "event_recv from bank 5"
            },
            {
                "customer-request-id": 8,
                "logical_clock": 60,
                "interface": "propogate_withdraw",
                "comment": "event_sent to branch 8"
            },
            {
                "customer-request-id": 8,
                "logical_clock": 61,
                "interface": "propogate_withdraw",
                "comment": "event_sent to branch 9"
            },
            {
                "customer-request-id": 8,
                "logical_clock": 62,
                "interface": "propogate_withdraw",
                "comment": "event_sent to branch 10"
            }
        ]
    },
    {
        "id": 5,
        "type": "branch",
        "events": [
            {
                "customer-request-id": 9,
                "logical_clock": 2,
                "interface": "deposit",
                "comment": "event_recv from customer 5"
            },
            {
                "customer-request-id": 9,
                "logical_clock": 3,
                "interface": "propogate_deposit",
                "comment": "event_sent to branch 1"
            },
            {
                "customer-request-id": 9,
                "logical_clock": 4,
                "interface": "propogate_deposit",
                "comment": "event_sent to branch 2"
            },
            {
                "customer-request-id": 5,
                "logical_clock": 11,
                "interface": "propogate_deposit",
                "comment": "event_recv from bank 3"
            },
            {
                "customer-request-id": 9,
                "logical_clock": 12,
                "interface": "propogate_deposit",
                "comment": "event_sent to branch 3"
            },
            {
                "customer-request-id": 1,
                "logical_clock": 16,
                "interface": "propogate_deposit",
                "comment": "event_recv from bank 1"
            },
            {
                "customer-request-id": 7,
                "logical_clock": 17,
                "interface": "propogate_deposit",
                "comment": "event_recv from bank 4"
            },
            {
                "customer-request-id": 11,
                "logical_clock": 18,
                "interface": "propogate_deposit",
                "comment": "event_recv from bank 6"
            },
            {
                "customer-request-id": 3,
                "logical_clock": 19,
                "interface": "propogate_deposit",
                "comment": "event_recv from bank 2"
            },
            {
                "customer-request-id": 17,
                "logical_clock": 20,
                "interface": "propogate_deposit",
                "comment": "event_recv from bank 9"
            },
            {
                "customer-request-id": 9,
                "logical_clock": 21,
                "interface": "propogate_deposit",
                "comment": "event_sent to branch 4"
            },
            {
                "customer-request-id": 15,
                "logical_clock": 22,
                "interface": "propogate_deposit",
                "comment": "event_recv from bank 8"
            },
            {
                "customer-request-id": 13,
                "logical_clock": 23,
                "interface": "propogate_deposit",
                "comment": "event_recv from bank 7"
            },
            {
                "customer-request-id": 9,
                "logical_clock": 24,
                "interface": "propogate_deposit",
                "comment": "event_sent to branch 6"
            },
            {
                "customer-request-id": 19,
                "logical_clock": 25,
                "interface": "propogate_deposit",
                "comment": "event_recv from bank 10"
            },
            {
                "customer-request-id": 9,
                "logical_clock": 26,
                "interface": "propogate_deposit",
                "comment": "event_sent to branch 7"
            },
            {
                "customer-request-id": 9,
                "logical_clock": 27,
                "interface": "propogate_deposit",
                "comment": "event_sent to branch 8"
            },
            {
                "customer-request-id": 9,
                "logical_clock": 28,
                "interface": "propogate_deposit",
                "comment": "event_sent to branch 9"
            },
            {
                "customer-request-id": 9,
                "logical_clock": 29,
                "interface": "propogate_deposit",
                "comment": "event_sent to branch 10"
            },
            {
                "customer-request-id": 10,
                "logical_clock": 30,
                "interface": "deposit",
                "comment": "event_recv from customer 5"
            },
            {
                "customer-request-id": 10,
                "logical_clock": 31,
                "interface": "propogate_withdraw",
                "comment": "event_sent to branch 1"
            },
            {
                "customer-request-id": 6,
                "logical_clock": 43,
                "interface": "propogate_withdraw",
                "comment": "event_recv from bank 3"
            },
            {
                "customer-request-id": 10,
                "logical_clock": 44,
                "interface": "propogate_withdraw",
                "comment": "event_sent to branch 2"
            },
            {
                "customer-request-id": 12,
                "logical_clock": 45,
                "interface": "propogate_withdraw",
                "comment": "event_recv from bank 6"
            },
            {
                "customer-request-id": 10,
                "logical_clock": 46,
                "interface": "propogate_withdraw",
                "comment": "event_sent to branch 3"
            },
            {
                "customer-request-id": 18,
                "logical_clock": 47,
                "interface": "propogate_withdraw",
                "comment": "event_recv from bank 9"
            },
            {
                "customer-request-id": 8,
                "logical_clock": 48,
                "interface": "propogate_withdraw",
                "comment": "event_recv from bank 4"
            },
            {
                "customer-request-id": 2,
                "logical_clock": 49,
                "interface": "propogate_withdraw",
                "comment": "event_recv from bank 1"
            },
            {
                "customer-request-id": 10,
                "logical_clock": 50,
                "interface": "propogate_withdraw",
                "comment": "event_sent to branch 4"
            },
            {
                "customer-request-id": 16,
                "logical_clock": 51,
                "interface": "propogate_withdraw",
                "comment": "event_recv from bank 8"
            },
            {
                "customer-request-id": 4,
                "logical_clock": 52,
                "interface": "propogate_withdraw",
                "comment": "event_recv from bank 2"
            },
            {
                "customer-request-id": 14,
                "logical_clock": 55,
                "interface": "propogate_withdraw",
                "comment": "event_recv from bank 7"
            },
            {
                "customer-request-id": 10,
                "logical_clock": 56,
                "interface": "propogate_withdraw",
                "comment": "event_sent to branch 6"
            },
            {
                "customer-request-id": 20,
                "logical_clock": 57,
                "interface": "propogate_withdraw",
                "comment": "event_recv from bank 10"
            },
            {
                "customer-request-id": 10,
                "logical_clock": 58,
                "interface": "propogate_withdraw",
                "comment": "event_sent to branch 7"
            },
            {
                "customer-request-id": 10,
                "logical_clock": 59,
                "interface": "propogate_withdraw",
                "comment": "event_sent to branch 8"
            },
            {
                "customer-request-id": 10,
                "logical_clock": 60,
                "interface": "propogate_withdraw",
                "comment": "event_sent to branch 9"
            },
            {
                "customer-request-id": 10,
                "logical_clock": 61,
                "interface": "propogate_withdraw",
                "comment": "event_sent to branch 10"
            }
        ]
    },
    {
        "id": 6,
        "type": "branch",
        "events": [
            {
                "customer-request-id": 11,
                "logical_clock": 2,
                "interface": "deposit",
                "comment": "event_recv from customer 6"
            },
            {
                "customer-request-id": 11,
                "logical_clock": 3,
                "interface": "propogate_deposit",
                "comment": "event_sent to branch 1"
            },
            {
                "customer-request-id": 11,
                "logical_clock": 4,
                "interface": "propogate_deposit",
                "comment": "event_sent to branch 2"
            },
            {
                "customer-request-id": 11,
                "logical_clock": 5,
                "interface": "propogate_deposit",
                "comment": "event_sent to branch 3"
            },
            {
                "customer-request-id": 11,
                "logical_clock": 6,
                "interface": "propogate_deposit",
                "comment": "event_sent to branch 4"
            },
            {
                "customer-request-id": 11,
                "logical_clock": 7,
                "interface": "propogate_deposit",
                "comment": "event_sent to branch 5"
            },
            {
                "customer-request-id": 11,
                "logical_clock": 8,
                "interface": "propogate_deposit",
                "comment": "event_sent to branch 7"
            },
            {
                "customer-request-id": 5,
                "logical_clock": 16,
                "interface": "propogate_deposit",
                "comment": "event_recv from bank 3"
            },
            {
                "customer-request-id": 1,
                "logical_clock": 17,
                "interface": "propogate_deposit",
                "comment": "event_recv from bank 1"
            },
            {
                "customer-request-id": 7,
                "logical_clock": 18,
                "interface": "propogate_deposit",
                "comment": "event_recv from bank 4"
            },
            {
                "customer-request-id": 11,
                "logical_clock": 19,
                "interface": "propogate_deposit",
                "comment": "event_sent to branch 8"
            },
            {
                "customer-request-id": 3,
                "logical_clock": 20,
                "interface": "propogate_deposit",
                "comment": "event_recv from bank 2"
            },
            {
                "customer-request-id": 17,
                "logical_clock": 21,
                "interface": "propogate_deposit",
                "comment": "event_recv from bank 9"
            },
            {
                "customer-request-id": 11,
                "logical_clock": 22,
                "interface": "propogate_deposit",
                "comment": "event_sent to branch 9"
            },
            {
                "customer-request-id": 15,
                "logical_clock": 23,
                "interface": "propogate_deposit",
                "comment": "event_recv from bank 8"
            },
            {
                "customer-request-id": 13,
                "logical_clock": 25,
                "interface": "propogate_deposit",
                "comment": "event_recv from bank 7"
            },
            {
                "customer-request-id": 9,
                "logical_clock": 26,
                "interface": "propogate_deposit",
                "comment": "event_recv from bank 5"
            },
            {
                "customer-request-id": 11,
                "logical_clock": 27,
                "interface": "propogate_deposit",
                "comment": "event_sent to branch 10"
            },
            {
                "customer-request-id": 19,
                "logical_clock": 28,
                "interface": "propogate_deposit",
                "comment": "event_recv from bank 10"
            },
            {
                "customer-request-id": 12,
                "logical_clock": 29,
                "interface": "deposit",
                "comment": "event_recv from customer 6"
            },
            {
                "customer-request-id": 12,
                "logical_clock": 30,
                "interface": "propogate_withdraw",
                "comment": "event_sent to branch 1"
            },
            {
                "customer-request-id": 12,
                "logical_clock": 31,
                "interface": "propogate_withdraw",
                "comment": "event_sent to branch 2"
            },
            {
                "customer-request-id": 12,
                "logical_clock": 32,
                "interface": "propogate_withdraw",
                "comment": "event_sent to branch 3"
            },
            {
                "customer-request-id": 12,
                "logical_clock": 33,
                "interface": "propogate_withdraw",
                "comment": "event_sent to branch 4"
            },
            {
                "customer-request-id": 12,
                "logical_clock": 34,
                "interface": "propogate_withdraw",
                "comment": "event_sent to branch 5"
            },
            {
                "customer-request-id": 6,
                "logical_clock": 44,
                "interface": "propogate_withdraw",
                "comment": "event_recv from bank 3"
            },
            {
                "customer-request-id": 12,
                "logical_clock": 45,
                "interface": "propogate_withdraw",
                "comment": "event_sent to branch 7"
            },
            {
                "customer-request-id": 12,
                "logical_clock": 46,
                "interface": "propogate_withdraw",
                "comment": "event_sent to branch 8"
            },
            {
                "customer-request-id": 18,
                "logical_clock": 47,
                "interface": "propogate_withdraw",
                "comment": "event_recv from bank 9"
            },
            {
                "customer-request-id": 12,
                "logical_clock": 48,
                "interface": "propogate_withdraw",
                "comment": "event_sent to branch 9"
            },
            {
                "customer-request-id": 8,
                "logical_clock": 57,
                "interface": "propogate_withdraw",
                "comment": "event_recv from bank 4"
            },
            {
                "customer-request-id": 2,
                "logical_clock": 58,
                "interface": "propogate_withdraw",
                "comment": "event_recv from bank 1"
            },
            {
                "customer-request-id": 12,
                "logical_clock": 59,
                "interface": "propogate_withdraw",
                "comment": "event_sent to branch 10"
            },
            {
                "customer-request-id": 16,
                "logical_clock": 60,
                "interface": "propogate_withdraw",
                "comment": "event_recv from bank 8"
            },
            {
                "customer-request-id": 10,
                "logical_clock": 61,
                "interface": "propogate_withdraw",
                "comment": "event_recv from bank 5"
            },
            {
                "customer-request-id": 4,
                "logical_clock": 62,
                "interface": "propogate_withdraw",
                "comment": "event_recv from bank 2"
            },
            {
                "customer-request-id": 14,
                "logical_clock": 63,
                "interface": "propogate_withdraw",
                "comment": "event_recv from bank 7"
            },
            {
                "customer-request-id": 20,
                "logical_clock": 64,
                "interface": "propogate_withdraw",
                "comment": "event_recv from bank 10"
            }
        ]
    },
    {
        "id": 7,
        "type": "branch",
        "events": [
            {
                "customer-request-id": 13,
                "logical_clock": 2,
                "interface": "deposit",
                "comment": "event_recv from customer 7"
            },
            {
                "customer-request-id": 13,
                "logical_clock": 3,
                "interface": "propogate_deposit",
                "comment": "event_sent to branch 1"
            },
            {
                "customer-request-id": 13,
                "logical_clock": 4,
                "interface": "propogate_deposit",
                "comment": "event_sent to branch 2"
            },
            {
                "customer-request-id": 13,
                "logical_clock": 5,
                "interface": "propogate_deposit",
                "comment": "event_sent to branch 3"
            },
            {
                "customer-request-id": 13,
                "logical_clock": 6,
                "interface": "propogate_deposit",
                "comment": "event_sent to branch 4"
            },
            {
                "customer-request-id": 11,
                "logical_clock": 9,
                "interface": "propogate_deposit",
                "comment": "event_recv from bank 6"
            },
            {
                "customer-request-id": 13,
                "logical_clock": 10,
                "interface": "propogate_deposit",
                "comment": "event_sent to branch 5"
            },
            {
                "customer-request-id": 5,
                "logical_clock": 21,
                "interface": "propogate_deposit",
                "comment": "event_recv from bank 3"
            },
            {
                "customer-request-id": 1,
                "logical_clock": 22,
                "interface": "propogate_deposit",
                "comment": "event_recv from bank 1"
            },
            {
                "customer-request-id": 7,
                "logical_clock": 23,
                "interface": "propogate_deposit",
                "comment": "event_recv from bank 4"
            },
            {
                "customer-request-id": 13,
                "logical_clock": 24,
                "interface": "propogate_deposit",
                "comment": "event_sent to branch 6"
            },
            {
                "customer-request-id": 3,
                "logical_clock": 25,
                "interface": "propogate_deposit",
                "comment": "event_recv from bank 2"
            },
            {
                "customer-request-id": 17,
                "logical_clock": 26,
                "interface": "propogate_deposit",
                "comment": "event_recv from bank 9"
            },
            {
                "customer-request-id": 13,
                "logical_clock": 27,
                "interface": "propogate_deposit",
                "comment": "event_sent to branch 8"
            },
            {
                "customer-request-id": 15,
                "logical_clock": 28,
                "interface": "propogate_deposit",
                "comment": "event_recv from bank 8"
            },
            {
                "customer-request-id": 9,
                "logical_clock": 29,
                "interface": "propogate_deposit",
                "comment": "event_recv from bank 5"
            },
            {
                "customer-request-id": 13,
                "logical_clock": 30,
                "interface": "propogate_deposit",
                "comment": "event_sent to branch 9"
            },
            {
                "customer-request-id": 19,
                "logical_clock": 31,
                "interface": "propogate_deposit",
                "comment": "event_recv from bank 10"
            },
            {
                "customer-request-id": 13,
                "logical_clock": 32,
                "interface": "propogate_deposit",
                "comment": "event_sent to branch 10"
            },
            {
                "customer-request-id": 14,
                "logical_clock": 33,
                "interface": "deposit",
                "comment": "event_recv from customer 7"
            },
            {
                "customer-request-id": 14,
                "logical_clock": 34,
                "interface": "propogate_withdraw",
                "comment": "event_sent to branch 1"
            },
            {
                "customer-request-id": 14,
                "logical_clock": 35,
                "interface": "propogate_withdraw",
                "comment": "event_sent to branch 2"
            },
            {
                "customer-request-id": 14,
                "logical_clock": 36,
                "interface": "propogate_withdraw",
                "comment": "event_sent to branch 3"
            },
            {
                "customer-request-id": 6,
                "logical_clock": 51,
                "interface": "propogate_withdraw",
                "comment": "event_recv from bank 3"
            },
            {
                "customer-request-id": 12,
                "logical_clock": 52,
                "interface": "propogate_withdraw",
                "comment": "event_recv from bank 6"
            },
            {
                "customer-request-id": 14,
                "logical_clock": 53,
                "interface": "propogate_withdraw",
                "comment": "event_sent to branch 4"
            },
            {
                "customer-request-id": 14,
                "logical_clock": 54,
                "interface": "propogate_withdraw",
                "comment": "event_sent to branch 5"
            },
            {
                "customer-request-id": 8,
                "logical_clock": 58,
                "interface": "propogate_withdraw",
                "comment": "event_recv from bank 4"
            },
            {
                "customer-request-id": 2,
                "logical_clock": 59,
                "interface": "propogate_withdraw",
                "comment": "event_recv from bank 1"
            },
            {
                "customer-request-id": 18,
                "logical_clock": 60,
                "interface": "propogate_withdraw",
                "comment": "event_recv from bank 9"
            },
            {
                "customer-request-id": 14,
                "logical_clock": 61,
                "interface": "propogate_withdraw",
                "comment": "event_sent to branch 6"
            },
            {
                "customer-request-id": 14,
                "logical_clock": 62,
                "interface": "propogate_withdraw",
                "comment": "event_sent to branch 8"
            },
            {
                "customer-request-id": 4,
                "logical_clock": 63,
                "interface": "propogate_withdraw",
                "comment": "event_recv from bank 2"
            },
            {
                "customer-request-id": 10,
                "logical_clock": 64,
                "interface": "propogate_withdraw",
                "comment": "event_recv from bank 5"
            },
            {
                "customer-request-id": 16,
                "logical_clock": 65,
                "interface": "propogate_withdraw",
                "comment": "event_recv from bank 8"
            },
            {
                "customer-request-id": 14,
                "logical_clock": 66,
                "interface": "propogate_withdraw",
                "comment": "event_sent to branch 9"
            },
            {
                "customer-request-id": 20,
                "logical_clock": 67,
                "interface": "propogate_withdraw",
                "comment": "event_recv from bank 10"
            },
            {
                "customer-request-id": 14,
                "logical_clock": 68,
                "interface": "propogate_withdraw",
                "comment": "event_sent to branch 10"
            }
        ]
    },
    {
        "id": 8,
        "type": "branch",
        "events": [
            {
                "customer-request-id": 15,
                "logical_clock": 2,
                "interface": "deposit",
                "comment": "event_recv from customer 8"
            },
            {
                "customer-request-id": 15,
                "logical_clock": 3,
                "interface": "propogate_deposit",
                "comment": "event_sent to branch 1"
            },
            {
                "customer-request-id": 15,
                "logical_clock": 4,
                "interface": "propogate_deposit",
                "comment": "event_sent to branch 2"
            },
            {
                "customer-request-id": 15,
                "logical_clock": 5,
                "interface": "propogate_deposit",
                "comment": "event_sent to branch 3"
            },
            {
                "customer-request-id": 15,
                "logical_clock": 6,
                "interface": "propogate_deposit",
                "comment": "event_sent to branch 4"
            },
            {
                "customer-request-id": 15,
                "logical_clock": 7,
                "interface": "propogate_deposit",
                "comment": "event_sent to branch 5"
            },
            {
                "customer-request-id": 11,
                "logical_clock": 20,
                "interface": "propogate_deposit",
                "comment": "event_recv from bank 6"
            },
            {
                "customer-request-id": 15,
                "logical_clock": 21,
                "interface": "propogate_deposit",
                "comment": "event_sent to branch 6"
            },
            {
                "customer-request-id": 5,
                "logical_clock": 22,
                "interface": "propogate_deposit",
                "comment": "event_recv from bank 3"
            },
            {
                "customer-request-id": 15,
                "logical_clock": 23,
                "interface": "propogate_deposit",
                "comment": "event_sent to branch 7"
            },
            {
                "customer-request-id": 7,
                "logical_clock": 24,
                "interface": "propogate_deposit",
                "comment": "event_recv from bank 4"
            },
            {
                "customer-request-id": 1,
                "logical_clock": 25,
                "interface": "propogate_deposit",
                "comment": "event_recv from bank 1"
            },
            {
                "customer-request-id": 17,
                "logical_clock": 26,
                "interface": "propogate_deposit",
                "comment": "event_recv from bank 9"
            },
            {
                "customer-request-id": 3,
                "logical_clock": 27,
                "interface": "propogate_deposit",
                "comment": "event_recv from bank 2"
            },
            {
                "customer-request-id": 15,
                "logical_clock": 28,
                "interface": "propogate_deposit",
                "comment": "event_sent to branch 9"
            },
            {
                "customer-request-id": 13,
                "logical_clock": 29,
                "interface": "propogate_deposit",
                "comment": "event_recv from bank 7"
            },
            {
                "customer-request-id": 15,
                "logical_clock": 30,
                "interface": "propogate_deposit",
                "comment": "event_sent to branch 10"
            },
            {
                "customer-request-id": 9,
                "logical_clock": 31,
                "interface": "propogate_deposit",
                "comment": "event_recv from bank 5"
            },
            {
                "customer-request-id": 19,
                "logical_clock": 34,
                "interface": "propogate_deposit",
                "comment": "event_recv from bank 10"
            },
            {
                "customer-request-id": 16,
                "logical_clock": 35,
                "interface": "deposit",
                "comment": "event_recv from customer 8"
            },
            {
                "customer-request-id": 16,
                "logical_clock": 36,
                "interface": "propogate_withdraw",
                "comment": "event_sent to branch 1"
            },
            {
                "customer-request-id": 16,
                "logical_clock": 37,
                "interface": "propogate_withdraw",
                "comment": "event_sent to branch 2"
            },
            {
                "customer-request-id": 16,
                "logical_clock": 38,
                "interface": "propogate_withdraw",
                "comment": "event_sent to branch 3"
            },
            {
                "customer-request-id": 16,
                "logical_clock": 39,
                "interface": "propogate_withdraw",
                "comment": "event_sent to branch 4"
            },
            {
                "customer-request-id": 12,
                "logical_clock": 47,
                "interface": "propogate_withdraw",
                "comment": "event_recv from bank 6"
            },
            {
                "customer-request-id": 16,
                "logical_clock": 48,
                "interface": "propogate_withdraw",
                "comment": "event_sent to branch 5"
            },
            {
                "customer-request-id": 6,
                "logical_clock": 53,
                "interface": "propogate_withdraw",
                "comment": "event_recv from bank 3"
            },
            {
                "customer-request-id": 16,
                "logical_clock": 54,
                "interface": "propogate_withdraw",
                "comment": "event_sent to branch 6"
            },
            {
                "customer-request-id": 8,
                "logical_clock": 61,
                "interface": "propogate_withdraw",
                "comment": "event_recv from bank 4"
            },
            {
                "customer-request-id": 2,
                "logical_clock": 62,
                "interface": "propogate_withdraw",
                "comment": "event_recv from bank 1"
            },
            {
                "customer-request-id": 18,
                "logical_clock": 63,
                "interface": "propogate_withdraw",
                "comment": "event_recv from bank 9"
            },
            {
                "customer-request-id": 16,
                "logical_clock": 64,
                "interface": "propogate_withdraw",
                "comment": "event_sent to branch 7"
            },
            {
                "customer-request-id": 14,
                "logical_clock": 65,
                "interface": "propogate_withdraw",
                "comment": "event_recv from bank 7"
            },
            {
                "customer-request-id": 16,
                "logical_clock": 66,
                "interface": "propogate_withdraw",
                "comment": "event_sent to branch 9"
            },
            {
                "customer-request-id": 10,
                "logical_clock": 67,
                "interface": "propogate_withdraw",
                "comment": "event_recv from bank 5"
            },
            {
                "customer-request-id": 4,
                "logical_clock": 68,
                "interface": "propogate_withdraw",
                "comment": "event_recv from bank 2"
            },
            {
                "customer-request-id": 16,
                "logical_clock": 69,
                "interface": "propogate_withdraw",
                "comment": "event_sent to branch 10"
            },
            {
                "customer-request-id": 20,
                "logical_clock": 70,
                "interface": "propogate_withdraw",
                "comment": "event_recv from bank 10"
            }
        ]
    },
    {
        "id": 9,
        "type": "branch",
        "events": [
            {
                "customer-request-id": 17,
                "logical_clock": 2,
                "interface": "deposit",
                "comment": "event_recv from customer 9"
            },
            {
                "customer-request-id": 17,
                "logical_clock": 3,
                "interface": "propogate_deposit",
                "comment": "event_sent to branch 1"
            },
            {
                "customer-request-id": 17,
                "logical_clock": 4,
                "interface": "propogate_deposit",
                "comment": "event_sent to branch 2"
            },
            {
                "customer-request-id": 17,
                "logical_clock": 5,
                "interface": "propogate_deposit",
                "comment": "event_sent to branch 3"
            },
            {
                "customer-request-id": 17,
                "logical_clock": 6,
                "interface": "propogate_deposit",
                "comment": "event_sent to branch 4"
            },
            {
                "customer-request-id": 17,
                "logical_clock": 7,
                "interface": "propogate_deposit",
                "comment": "event_sent to branch 5"
            },
            {
                "customer-request-id": 17,
                "logical_clock": 8,
                "interface": "propogate_deposit",
                "comment": "event_sent to branch 6"
            },
            {
                "customer-request-id": 17,
                "logical_clock": 9,
                "interface": "propogate_deposit",
                "comment": "event_sent to branch 7"
            },
            {
                "customer-request-id": 17,
                "logical_clock": 10,
                "interface": "propogate_deposit",
                "comment": "event_sent to branch 8"
            },
            {
                "customer-request-id": 11,
                "logical_clock": 23,
                "interface": "propogate_deposit",
                "comment": "event_recv from bank 6"
            },
            {
                "customer-request-id": 5,
                "logical_clock": 24,
                "interface": "propogate_deposit",
                "comment": "event_recv from bank 3"
            },
            {
                "customer-request-id": 17,
                "logical_clock": 25,
                "interface": "propogate_deposit",
                "comment": "event_sent to branch 10"
            },
            {
                "customer-request-id": 7,
                "logical_clock": 26,
                "interface": "propogate_deposit",
                "comment": "event_recv from bank 4"
            },
            {
                "customer-request-id": 15,
                "logical_clock": 29,
                "interface": "propogate_deposit",
                "comment": "event_recv from bank 8"
            },
            {
                "customer-request-id": 1,
                "logical_clock": 30,
                "interface": "propogate_deposit",
                "comment": "event_recv from bank 1"
            },
            {
                "customer-request-id": 3,
                "logical_clock": 31,
                "interface": "propogate_deposit",
                "comment": "event_recv from bank 2"
            },
            {
                "customer-request-id": 13,
                "logical_clock": 32,
                "interface": "propogate_deposit",
                "comment": "event_recv from bank 7"
            },
            {
                "customer-request-id": 9,
                "logical_clock": 33,
                "interface": "propogate_deposit",
                "comment": "event_recv from bank 5"
            },
            {
                "customer-request-id": 18,
                "logical_clock": 34,
                "interface": "deposit",
                "comment": "event_recv from customer 9"
            },
            {
                "customer-request-id": 18,
                "logical_clock": 35,
                "interface": "propogate_withdraw",
                "comment": "event_sent to branch 1"
            },
            {
                "customer-request-id": 18,
                "logical_clock": 36,
                "interface": "propogate_withdraw",
                "comment": "event_sent to branch 2"
            },
            {
                "customer-request-id": 19,
                "logical_clock": 39,
                "interface": "propogate_deposit",
                "comment": "event_recv from bank 10"
            },
            {
                "customer-request-id": 18,
                "logical_clock": 40,
                "interface": "propogate_withdraw",
                "comment": "event_sent to branch 3"
            },
            {
                "customer-request-id": 18,
                "logical_clock": 41,
                "interface": "propogate_withdraw",
                "comment": "event_sent to branch 4"
            },
            {
                "customer-request-id": 18,
                "logical_clock": 42,
                "interface": "propogate_withdraw",
                "comment": "event_sent to branch 5"
            },
            {
                "customer-request-id": 18,
                "logical_clock": 43,
                "interface": "propogate_withdraw",
                "comment": "event_sent to branch 6"
            },
            {
                "customer-request-id": 18,
                "logical_clock": 44,
                "interface": "propogate_withdraw",
                "comment": "event_sent to branch 7"
            },
            {
                "customer-request-id": 12,
                "logical_clock": 49,
                "interface": "propogate_withdraw",
                "comment": "event_recv from bank 6"
            },
            {
                "customer-request-id": 6,
                "logical_clock": 55,
                "interface": "propogate_withdraw",
                "comment": "event_recv from bank 3"
            },
            {
                "customer-request-id": 18,
                "logical_clock": 56,
                "interface": "propogate_withdraw",
                "comment": "event_sent to branch 8"
            },
            {
                "customer-request-id": 8,
                "logical_clock": 62,
                "interface": "propogate_withdraw",
                "comment": "event_recv from bank 4"
            },
            {
                "customer-request-id": 2,
                "logical_clock": 63,
                "interface": "propogate_withdraw",
                "comment": "event_recv from bank 1"
            },
            {
                "customer-request-id": 18,
                "logical_clock": 64,
                "interface": "propogate_withdraw",
                "comment": "event_sent to branch 10"
            },
            {
                "customer-request-id": 16,
                "logical_clock": 67,
                "interface": "propogate_withdraw",
                "comment": "event_recv from bank 8"
            },
            {
                "customer-request-id": 14,
                "logical_clock": 68,
                "interface": "propogate_withdraw",
                "comment": "event_recv from bank 7"
            },
            {
                "customer-request-id": 4,
                "logical_clock": 69,
                "interface": "propogate_withdraw",
                "comment": "event_recv from bank 2"
            },
            {
                "customer-request-id": 10,
                "logical_clock": 70,
                "interface": "propogate_withdraw",
                "comment": "event_recv from bank 5"
            },
            {
                "customer-request-id": 20,
                "logical_clock": 73,
                "interface": "propogate_withdraw",
                "comment": "event_recv from bank 10"
            }
        ]
    },
    {
        "id": 10,
        "type": "branch",
        "events": [
            {
                "customer-request-id": 19,
                "logical_clock": 2,
                "interface": "deposit",
                "comment": "event_recv from customer 10"
            },
            {
                "customer-request-id": 19,
                "logical_clock": 3,
                "interface": "propogate_deposit",
                "comment": "event_sent to branch 1"
            },
            {
                "customer-request-id": 19,
                "logical_clock": 4,
                "interface": "propogate_deposit",
                "comment": "event_sent to branch 2"
            },
            {
                "customer-request-id": 19,
                "logical_clock": 5,
                "interface": "propogate_deposit",
                "comment": "event_sent to branch 3"
            },
            {
                "customer-request-id": 19,
                "logical_clock": 6,
                "interface": "propogate_deposit",
                "comment": "event_sent to branch 4"
            },
            {
                "customer-request-id": 19,
                "logical_clock": 7,
                "interface": "propogate_deposit",
                "comment": "event_sent to branch 5"
            },
            {
                "customer-request-id": 19,
                "logical_clock": 8,
                "interface": "propogate_deposit",
                "comment": "event_sent to branch 6"
            },
            {
                "customer-request-id": 11,
                "logical_clock": 28,
                "interface": "propogate_deposit",
                "comment": "event_recv from bank 6"
            },
            {
                "customer-request-id": 19,
                "logical_clock": 29,
                "interface": "propogate_deposit",
                "comment": "event_sent to branch 7"
            },
            {
                "customer-request-id": 5,
                "logical_clock": 30,
                "interface": "propogate_deposit",
                "comment": "event_recv from bank 3"
            },
            {
                "customer-request-id": 17,
                "logical_clock": 31,
                "interface": "propogate_deposit",
                "comment": "event_recv from bank 9"
            },
            {
                "customer-request-id": 7,
                "logical_clock": 32,
                "interface": "propogate_deposit",
                "comment": "event_recv from bank 4"
            },
            {
                "customer-request-id": 19,
                "logical_clock": 33,
                "interface": "propogate_deposit",
                "comment": "event_sent to branch 8"
            },
            {
                "customer-request-id": 15,
                "logical_clock": 34,
                "interface": "propogate_deposit",
                "comment": "event_recv from bank 8"
            },
            {
                "customer-request-id": 3,
                "logical_clock": 35,
                "interface": "propogate_deposit",
                "comment": "event_recv from bank 2"
            },
            {
                "customer-request-id": 1,
                "logical_clock": 36,
                "interface": "propogate_deposit",
                "comment": "event_recv from bank 1"
            },
            {
                "customer-request-id": 13,
                "logical_clock": 37,
                "interface": "propogate_deposit",
                "comment": "event_recv from bank 7"
            },
            {
                "customer-request-id": 19,
                "logical_clock": 38,
                "interface": "propogate_deposit",
                "comment": "event_sent to branch 9"
            },
            {
                "customer-request-id": 9,
                "logical_clock": 39,
                "interface": "propogate_deposit",
                "comment": "event_recv from bank 5"
            },
            {
                "customer-request-id": 20,
                "logical_clock": 40,
                "interface": "deposit",
                "comment": "event_recv from customer 10"
            },
            {
                "customer-request-id": 20,
                "logical_clock": 41,
                "interface": "propogate_withdraw",
                "comment": "event_sent to branch 1"
            },
            {
                "customer-request-id": 20,
                "logical_clock": 42,
                "interface": "propogate_withdraw",
                "comment": "event_sent to branch 2"
            },
            {
                "customer-request-id": 20,
                "logical_clock": 43,
                "interface": "propogate_withdraw",
                "comment": "event_sent to branch 3"
            },
            {
                "customer-request-id": 20,
                "logical_clock": 44,
                "interface": "propogate_withdraw",
                "comment": "event_sent to branch 4"
            },
            {
                "customer-request-id": 20,
                "logical_clock": 45,
                "interface": "propogate_withdraw",
                "comment": "event_sent to branch 5"
            },
            {
                "customer-request-id": 12,
                "logical_clock": 60,
                "interface": "propogate_withdraw",
                "comment": "event_recv from bank 6"
            },
            {
                "customer-request-id": 6,
                "logical_clock": 61,
                "interface": "propogate_withdraw",
                "comment": "event_recv from bank 3"
            },
            {
                "customer-request-id": 20,
                "logical_clock": 62,
                "interface": "propogate_withdraw",
                "comment": "event_sent to branch 6"
            },
            {
                "customer-request-id": 8,
                "logical_clock": 63,
                "interface": "propogate_withdraw",
                "comment": "event_recv from bank 4"
            },
            {
                "customer-request-id": 20,
                "logical_clock": 64,
                "interface": "propogate_withdraw",
                "comment": "event_sent to branch 7"
            },
            {
                "customer-request-id": 18,
                "logical_clock": 65,
                "interface": "propogate_withdraw",
                "comment": "event_recv from bank 9"
            },
            {
                "customer-request-id": 2,
                "logical_clock": 66,
                "interface": "propogate_withdraw",
                "comment": "event_recv from bank 1"
            },
            {
                "customer-request-id": 20,
                "logical_clock": 67,
                "interface": "propogate_withdraw",
                "comment": "event_sent to branch 8"
            },
            {
                "customer-request-id": 16,
                "logical_clock": 70,
                "interface": "propogate_withdraw",
                "comment": "event_recv from bank 8"
            },
            {
                "customer-request-id": 14,
                "logical_clock": 71,
                "interface": "propogate_withdraw",
                "comment": "event_recv from bank 7"
            },
            {
                "customer-request-id": 20,
                "logical_clock": 72,
                "interface": "propogate_withdraw",
                "comment": "event_sent to branch 9"
            },
            {
                "customer-request-id": 4,
                "logical_clock": 73,
                "interface": "propogate_withdraw",
                "comment": "event_recv from bank 2"
            },
            {
                "customer-request-id": 10,
                "logical_clock": 74,
                "interface": "propogate_withdraw",
                "comment": "event_recv from bank 5"
            }
        ]
    }
]